{"stats":{"minecraft:crafted":{"minecraft:brick":40,"minecraft:oak_planks":1506,"minecraft:smooth_stone":49,"minecraft:cobblestone_slab":90,"minecraft:barrel":9,"minecraft:cooked_chicken":11,"minecraft:loom":1,"minecraft:cobblestone_stairs":128,"minecraft:stone":549,"minecraft:cooked_mutton":19,"minecraft:glass":40,"minecraft:hopper":4,"minecraft:stone_brick_slab":24,"minecraft:bow":1,"minecraft:chest":53,"minecraft:oak_button":1,"minecraft:stone_bricks":320,"minecraft:oak_fence":84,"minecraft:flower_pot":4,"minecraft:smoker":1,"minecraft:dropper":1,"minecraft:oak_slab":36,"minecraft:cooked_porkchop":6,"minecraft:crafting_table":24,"minecraft:spruce_planks":1390,"minecraft:polished_andesite_stairs":8,"minecraft:wooden_pickaxe":1,"minecraft:baked_potato":1,"minecraft:spruce_door":12,"minecraft:campfire":31,"minecraft:dispenser":6,"minecraft:stone_brick_stairs":76,"minecraft:spruce_trapdoor":64,"minecraft:dark_oak_slab":12,"minecraft:diamond_pickaxe":3,"minecraft:shield":1,"minecraft:stick":520,"minecraft:iron_ingot":563,"minecraft:iron_pickaxe":25,"minecraft:andesite_stairs":32,"minecraft:gold_ingot":120,"minecraft:redstone_torch":4,"minecraft:composter":2,"minecraft:spruce_fence_gate":36,"minecraft:shears":4,"minecraft:polished_andesite":32,"minecraft:coal":594,"minecraft:smooth_stone_slab":6,"minecraft:golden_chestplate":1,"minecraft:iron_nugget":63,"minecraft:spruce_button":19,"minecraft:furnace":27,"minecraft:blast_furnace":9,"minecraft:piston":2,"minecraft:bone_meal":165,"minecraft:spruce_fence":126,"minecraft:polished_andesite_slab":18,"minecraft:glass_pane":48,"minecraft:flint_and_steel":1,"minecraft:lantern":7,"minecraft:spruce_stairs":148,"minecraft:polished_diorite":32,"minecraft:iron_axe":14,"minecraft:iron_hoe":4,"minecraft:spruce_slab":444,"minecraft:stone_pickaxe":1,"minecraft:cobblestone_wall":70,"minecraft:redstone_block":1,"minecraft:dark_oak_planks":124,"minecraft:cooked_beef":96,"minecraft:coal_block":58,"minecraft:diamond_sword":1,"minecraft:dark_oak_stairs":48,"minecraft:iron_sword":2,"minecraft:cooked_salmon":2,"minecraft:bucket":9,"minecraft:bread":37,"minecraft:air":0,"minecraft:oak_fence_gate":1,"minecraft:oak_boat":2,"minecraft:andesite_slab":12,"minecraft:oak_stairs":180,"minecraft:iron_shovel":16,"minecraft:stonecutter":1,"minecraft:white_bed":2,"minecraft:torch":252,"minecraft:diorite_slab":12},"minecraft:dropped":{"minecraft:iron_sword":2,"minecraft:porkchop":6,"minecraft:brown_mushroom":1,"minecraft:lapis_lazuli":10,"minecraft:cooked_beef":2,"minecraft:oak_log":17,"minecraft:diamond":1,"minecraft:crafting_table":3,"minecraft:cooked_porkchop":2,"minecraft:lantern":10,"minecraft:leather":13,"minecraft:red_mushroom":1,"minecraft:flint":8,"minecraft:emerald":1,"minecraft:dirt":19,"minecraft:dark_oak_log":35,"minecraft:cornflower":1,"minecraft:mutton":3,"minecraft:iron_pickaxe":7,"minecraft:white_wool":6,"minecraft:bone":22,"minecraft:gravel":63,"minecraft:stone_axe":1,"minecraft:cooked_chicken":1,"minecraft:wheat":4,"minecraft:rotten_flesh":26,"minecraft:oak_planks":10,"minecraft:glowstone_dust":59,"minecraft:cooked_mutton":3,"minecraft:white_bed":3,"minecraft:poppy":3,"minecraft:gunpowder":18,"minecraft:beetroot_seeds":1,"minecraft:iron_ore":7,"minecraft:arrow":37,"minecraft:egg":3,"minecraft:iron_ingot":33,"minecraft:bread":1,"minecraft:oak_slab":6,"minecraft:wheat_seeds":22,"minecraft:feather":19,"minecraft:cobblestone":88,"minecraft:apple":1,"minecraft:granite":49,"minecraft:coal":35,"minecraft:stick":11,"minecraft:diorite":66,"minecraft:torch":12,"minecraft:iron_shovel":2,"minecraft:string":17,"minecraft:bucket":1,"minecraft:redstone":4,"minecraft:dandelion":2,"minecraft:furnace":1,"minecraft:chicken":1,"minecraft:iron_hoe":1,"minecraft:spruce_fence":1,"minecraft:shears":1,"minecraft:hay_block":29,"minecraft:shield":3,"minecraft:oak_button":2,"minecraft:spruce_planks":12,"minecraft:diamond_pickaxe":1,"minecraft:andesite":6,"minecraft:spider_eye":18,"minecraft:stone_bricks":1,"minecraft:spruce_log":216,"minecraft:bow":12,"minecraft:stone_pickaxe":2,"minecraft:wooden_pickaxe":3,"minecraft:black_wool":1},"minecraft:custom":{"minecraft:animals_bred":144,"minecraft:interact_with_crafting_table":381,"minecraft:open_barrel":318,"minecraft:bell_ring":62,"minecraft:leave_game":33,"minecraft:time_since_death":43787,"minecraft:sprint_one_cm":4316627,"minecraft:damage_blocked_by_shield":1845,"minecraft:drop":272,"minecraft:talked_to_villager":97,"minecraft:deaths":26,"minecraft:jump":18806,"minecraft:walk_on_water_one_cm":106436,"minecraft:enchant_item":2,"minecraft:interact_with_furnace":284,"minecraft:play_one_minute":1271554,"minecraft:interact_with_loom":3,"minecraft:sleep_in_bed":49,"minecraft:damage_dealt":70716,"minecraft:player_kills":2,"minecraft:crouch_one_cm":116086,"minecraft:interact_with_smoker":43,"minecraft:inspect_dispenser":17,"minecraft:inspect_dropper":3,"minecraft:mob_kills":437,"minecraft:inspect_hopper":29,"minecraft:interact_with_campfire":5,"minecraft:climb_one_cm":4954,"minecraft:walk_one_cm":3862253,"minecraft:sneak_time":31306,"minecraft:walk_under_water_one_cm":24499,"minecraft:boat_one_cm":28070,"minecraft:interact_with_blast_furnace":69,"minecraft:interact_with_stonecutter":3,"minecraft:time_since_rest":963,"minecraft:damage_taken":17350,"minecraft:minecart_one_cm":98576,"minecraft:swim_one_cm":34526,"minecraft:fly_one_cm":3237954,"minecraft:open_chest":578,"minecraft:fall_one_cm":309683},"minecraft:killed":{"minecraft:spider":45,"minecraft:skeleton":86,"minecraft:chicken":12,"minecraft:silverfish":16,"minecraft:pig":5,"minecraft:creeper":25,"minecraft:sheep":15,"minecraft:pillager":2,"minecraft:zombie":158,"minecraft:cow":70,"minecraft:enderman":1},"minecraft:used":{"minecraft:beetroot":5,"minecraft:iron_shovel":3277,"minecraft:dispenser":10,"minecraft:spruce_slab":237,"minecraft:poppy":1,"minecraft:chest":57,"minecraft:stone":9,"minecraft:iron_sword":618,"minecraft:grass":17,"minecraft:carrot":141,"minecraft:snowball":4,"minecraft:azure_bluet":1,"minecraft:obsidian":10,"minecraft:lantern":24,"minecraft:polished_andesite_stairs":8,"minecraft:dark_oak_slab":12,"minecraft:stone_brick_stairs":73,"minecraft:stone_bricks":197,"minecraft:bow":25,"minecraft:hay_block":24,"minecraft:sweet_berries":152,"minecraft:oak_sapling":233,"minecraft:furnace":27,"minecraft:beetroot_seeds":12,"minecraft:egg":19,"minecraft:potato":2,"minecraft:dark_oak_sapling":9,"minecraft:dark_oak_stairs":47,"minecraft:diorite":83,"minecraft:spruce_door":12,"minecraft:dropper":3,"minecraft:stone_pickaxe":39,"minecraft:oak_planks":452,"minecraft:wooden_pickaxe":8,"minecraft:redstone_block":11,"minecraft:composter":5,"minecraft:oak_leaves":252,"minecraft:white_wool":2,"minecraft:loom":1,"minecraft:blast_furnace":15,"minecraft:shears":336,"minecraft:pumpkin_seeds":1,"minecraft:redstone_torch":80,"minecraft:string":3,"minecraft:bread":26,"minecraft:brown_wool":1,"minecraft:gravel":27,"minecraft:polished_andesite_slab":18,"minecraft:diamond_sword":574,"minecraft:coal_block":1,"minecraft:andesite":115,"minecraft:smooth_stone_slab":7,"minecraft:oak_boat":2,"minecraft:diorite_slab":13,"minecraft:bone_meal":189,"minecraft:oak_fence":90,"minecraft:rose_bush":2,"minecraft:flint_and_steel":4,"minecraft:redstone":19,"minecraft:spruce_planks":256,"minecraft:cooked_salmon":2,"minecraft:cooked_chicken":10,"minecraft:netherrack":40,"minecraft:torch":245,"minecraft:dirt":3191,"minecraft:hopper":9,"minecraft:spruce_stairs":161,"minecraft:cobblestone_wall":25,"minecraft:granite":56,"minecraft:spruce_fence":130,"minecraft:oak_fence_gate":1,"minecraft:polished_diorite":33,"minecraft:iron_hoe":771,"minecraft:stone_brick_slab":25,"minecraft:dark_oak_planks":2,"minecraft:iron_axe":2478,"minecraft:oak_stairs":127,"minecraft:spruce_button":17,"minecraft:barrel":9,"minecraft:minecart":3,"minecraft:cooked_beef":119,"minecraft:pumpkin":5,"minecraft:wheat_seeds":1439,"minecraft:cooked_mutton":23,"minecraft:water_bucket":64,"minecraft:iron_ore":3,"minecraft:cobblestone_stairs":153,"minecraft:polished_andesite":12,"minecraft:baked_potato":1,"minecraft:andesite_slab":15,"minecraft:spruce_sign":1,"minecraft:cobblestone_slab":95,"minecraft:stonecutter":2,"minecraft:spruce_fence_gate":34,"minecraft:gold_ore":2,"minecraft:crafting_table":39,"minecraft:oak_slab":28,"minecraft:white_bed":15,"minecraft:campfire":31,"minecraft:spruce_log":1,"minecraft:smoker":2,"minecraft:oak_log":514,"minecraft:piston":2,"minecraft:flower_pot":4,"minecraft:black_wool":1,"minecraft:diamond_pickaxe":2438,"minecraft:apple":17,"minecraft:iron_pickaxe":5262,"minecraft:oak_button":1,"minecraft:spruce_trapdoor":72,"minecraft:spruce_sapling":50,"minecraft:chiseled_stone_bricks":1,"minecraft:cobblestone":1335,"minecraft:cooked_porkchop":6,"minecraft:andesite_stairs":34,"minecraft:bucket":70,"minecraft:glass_pane":33,"minecraft:yellow_bed":1,"minecraft:smooth_stone":5},"minecraft:killed_by":{"minecraft:creeper":6,"minecraft:zombie":2,"minecraft:player":2,"minecraft:skeleton":12},"minecraft:mined":{"minecraft:spruce_planks":34,"minecraft:oak_sapling":78,"minecraft:white_bed":14,"minecraft:farmland":8,"minecraft:andesite_stairs":2,"minecraft:cobblestone_stairs":35,"minecraft:obsidian":22,"minecraft:spruce_trapdoor":18,"minecraft:granite":247,"minecraft:grass_block":1612,"minecraft:coal_block":1,"minecraft:polished_diorite":1,"minecraft:composter":2,"minecraft:hopper":5,"minecraft:oxeye_daisy":1,"minecraft:magma_block":7,"minecraft:glowstone":24,"minecraft:iron_ore":619,"minecraft:barrel":1,"minecraft:pumpkin":4,"minecraft:azure_bluet":1,"minecraft:dark_oak_stairs":5,"minecraft:oak_stairs":21,"minecraft:spruce_slab":24,"minecraft:tripwire":3,"minecraft:brown_mushroom":1,"minecraft:clay":10,"minecraft:torch":10,"minecraft:blast_furnace":6,"minecraft:poppy":2,"minecraft:chest":8,"minecraft:spruce_wall_sign":1,"minecraft:nether_quartz_ore":38,"minecraft:cobblestone":82,"minecraft:oak_planks":34,"minecraft:wall_torch":12,"minecraft:seagrass":1,"minecraft:stone_stairs":1,"minecraft:wheat":735,"minecraft:pumpkin_stem":1,"minecraft:stone_brick_stairs":5,"minecraft:smooth_stone_slab":1,"minecraft:grass":1057,"minecraft:oak_log":970,"minecraft:beetroots":7,"minecraft:dirt":1433,"minecraft:stonecutter":1,"minecraft:dispenser":4,"minecraft:netherrack":42,"minecraft:oak_leaves":1386,"minecraft:diamond_ore":41,"minecraft:dark_oak_leaves":106,"minecraft:dark_oak_log":109,"minecraft:spruce_fence":6,"minecraft:redstone_wire":3,"minecraft:spruce_leaves":62,"minecraft:hay_block":15,"minecraft:diorite_slab":1,"minecraft:redstone_ore":147,"minecraft:spruce_sapling":6,"minecraft:furnace":11,"minecraft:carrots":30,"minecraft:andesite":393,"minecraft:potatoes":3,"minecraft:cobblestone_slab":5,"minecraft:vine":2,"minecraft:lantern":1,"minecraft:stone":4934,"minecraft:redstone_wall_torch":21,"minecraft:podzol":2,"minecraft:oak_slab":10,"minecraft:redstone_block":11,"minecraft:stone_brick_slab":2,"minecraft:dandelion":1,"minecraft:oak_fence":18,"minecraft:crafting_table":14,"minecraft:cornflower":1,"minecraft:spruce_button":2,"minecraft:emerald_ore":7,"minecraft:dropper":3,"minecraft:andesite_slab":2,"minecraft:campfire":8,"minecraft:lapis_ore":20,"minecraft:diorite":306,"minecraft:spruce_stairs":15,"minecraft:cobblestone_wall":1,"minecraft:redstone_torch":55,"minecraft:sweet_berry_bush":30,"minecraft:spruce_log":584,"minecraft:grass_path":17,"minecraft:coal_ore":510,"minecraft:gravel":196,"minecraft:cobweb":14,"minecraft:oak_button":1,"minecraft:polished_andesite":1,"minecraft:spruce_fence_gate":4,"minecraft:stone_bricks":12,"minecraft:gold_ore":129,"minecraft:fern":1,"minecraft:infested_stone":7},"minecraft:picked_up":{"minecraft:wheat":854,"minecraft:redstone_block":11,"minecraft:oak_stairs":22,"minecraft:stone_brick_stairs":4,"minecraft:string":71,"minecraft:smooth_stone_slab":1,"minecraft:beetroot":5,"minecraft:spruce_planks":166,"minecraft:rose_bush":2,"minecraft:redstone_torch":78,"minecraft:cobblestone_slab":7,"minecraft:iron_pickaxe":3,"minecraft:coal_block":1,"minecraft:furnace":12,"minecraft:stick":141,"minecraft:composter":3,"minecraft:oak_fence":18,"minecraft:torch":82,"minecraft:spruce_stairs":15,"minecraft:porkchop":15,"minecraft:diorite":393,"minecraft:rotten_flesh":157,"minecraft:obsidian":22,"minecraft:cobblestone":5352,"minecraft:feather":21,"minecraft:cooked_beef":25,"minecraft:water_bucket":3,"minecraft:andesite":392,"minecraft:brown_wool":1,"minecraft:smoker":1,"minecraft:potato":4,"minecraft:flint":16,"minecraft:lapis_lazuli":174,"minecraft:dirt":3526,"minecraft:lantern":49,"minecraft:bone":90,"minecraft:bow":19,"minecraft:stonecutter":1,"minecraft:wheat_seeds":2610,"minecraft:glowstone_dust":59,"minecraft:oak_planks":150,"minecraft:cooked_porkchop":2,"minecraft:dropper":3,"minecraft:sand":40,"minecraft:stripped_spruce_log":2,"minecraft:dark_oak_log":99,"minecraft:barrel":1,"minecraft:iron_hoe":1,"minecraft:polished_andesite":1,"minecraft:spruce_fence_gate":4,"minecraft:dispenser":4,"minecraft:diamond":37,"minecraft:granite":337,"minecraft:bone_meal":20,"minecraft:grass":38,"minecraft:emerald":8,"minecraft:spruce_button":2,"minecraft:spruce_sign":1,"minecraft:bread":1,"minecraft:oak_sapling":248,"minecraft:netherrack":40,"minecraft:oak_leaves":273,"minecraft:andesite_slab":3,"minecraft:diamond_pickaxe":1,"minecraft:charcoal":30,"minecraft:crafting_table":19,"minecraft:azure_bluet":1,"minecraft:chicken":13,"minecraft:clay_ball":40,"minecraft:brown_mushroom":1,"minecraft:wooden_pickaxe":2,"minecraft:diorite_slab":1,"minecraft:shield":3,"minecraft:cornflower":1,"minecraft:stone_stairs":1,"minecraft:beef":124,"minecraft:andesite_stairs":2,"minecraft:oak_boat":1,"minecraft:poppy":4,"minecraft:spruce_slab":26,"minecraft:minecart":4,"minecraft:chest":9,"minecraft:spruce_trapdoor":18,"minecraft:egg":24,"minecraft:dark_oak_sapling":5,"minecraft:stone":139,"minecraft:spruce_fence":7,"minecraft:carrot":129,"minecraft:redstone":629,"minecraft:dark_oak_planks":36,"minecraft:arrow":100,"minecraft:beetroot_seeds":13,"minecraft:hay_block":53,"minecraft:mutton":27,"minecraft:rail":2,"minecraft:white_wool":22,"minecraft:oxeye_daisy":1,"minecraft:salmon":1,"minecraft:leather":65,"minecraft:yellow_dye":16,"minecraft:red_mushroom":3,"minecraft:oak_log":1290,"minecraft:yellow_bed":1,"minecraft:cobblestone_wall":3,"minecraft:gunpowder":27,"minecraft:cobblestone_stairs":35,"minecraft:cooked_mutton":7,"minecraft:apple":19,"minecraft:stone_bricks":12,"minecraft:iron_ingot":89,"minecraft:stone_pickaxe":2,"minecraft:iron_ore":610,"minecraft:iron_sword":2,"minecraft:dark_oak_stairs":4,"minecraft:oak_slab":10,"minecraft:milk_bucket":1,"minecraft:pumpkin":5,"minecraft:sweet_berries":159,"minecraft:stone_brick_slab":4,"minecraft:quartz":38,"minecraft:dandelion":4,"minecraft:gravel":222,"minecraft:spruce_sapling":56,"minecraft:blast_furnace":6,"minecraft:white_bed":16,"minecraft:spruce_log":874,"minecraft:gold_ore":130,"minecraft:spider_eye":26,"minecraft:pumpkin_seeds":1,"minecraft:polished_diorite":1,"minecraft:oak_button":2,"minecraft:baked_potato":1,"minecraft:black_wool":2,"minecraft:coal":740,"minecraft:hopper":5},"minecraft:broken":{"minecraft:iron_shovel":12,"minecraft:shears":1,"minecraft:diamond_pickaxe":1,"minecraft:iron_sword":2,"minecraft:golden_chestplate":1,"minecraft:iron_hoe":3,"minecraft:iron_axe":9,"minecraft:iron_pickaxe":21}},"DataVersion":1976}